{
	"ticker": "LIFCO-B.ST",
	"name": "Lifco AB",
	"group": "Serial Acquirers",
	"confidence": "low",
	"confidenceReason": "Priced for perfection at 44.6x P/E on cyclical industrials. Zero margin of safety. European construction slowdown will compress multiple.",
	"marketCap": "135.1B SEK",
	"sharpeRatio": 0.14,
	"expectedCAGR": "4% - 13%",
	"expectedVolatility": "~28%",
	"valuation": {
		"trailingPE": 37.2,
		"forwardPE": 37.3,
		"pegRatio": null,
		"evEbitda": 20,
		"evFcf": 29
	},
	"metrics": {
		"fcfMargin": "~16%",
		"fcfYield": "~3%",
		"roic": "15.0% - 20.0%",
		"roe": "19.5%",
		"netDebtEbitda": "1.3x",
		"ruleOf40": "22%"
	},
	"targetPrice": "382 SEK",
	"bullCase": "Provides necessary industrial diversification (dental, demolition) with a stellar historical compounding track record, mitigating pure software concentration risk.",
	"bearCase": "Priced for absolute macroeconomic perfection. Applying a 44.6x software-like multiple to cyclical physical industrials leaves a zero margin of safety. Any European construction slowdown will immediately compress this multiple.",
	"currentPrice": "297 SEK",
	"consensus": {
		"tipranks": "382 SEK",
		"yahoo": "356 SEK"
	},
	"cagrModel": {
		"horizon": 5,
		"ttmEPS": 8,
		"epsGrowth": "12%",
		"dividendYield": "1%",
		"exitPE": {
			"bear": 28,
			"base": 35,
			"bull": 42
		},
		"scenarios": {
			"bear": "4%",
			"base": "9%",
			"bull": "13%"
		},
		"basis": "10yr avg PE"
	},
	"lastUpdated": "2026-03-10T14:19:38.214Z"
}
