{
	"ticker": "ARES",
	"name": "Ares Management",
	"group": "Financials & Alt Assets",
	"bullCase": "Ares is the largest pure-play private credit manager with $450B+ AUM, growing 20%+ annually in the direct lending boom. Its permanent capital vehicles (ARCC, ACRE) provide structural FRE visibility. Credit spreads remaining elevated extends the private credit wave. Growing insurance channel (via Aspida Life) adds recurring fee flow.",
	"bearCase": "A sharp credit cycle downturn with default rates spiking would impair Ares' direct lending book and compress marks on private equity. The 5% dividend yield is funded by distributable earnings — any payout cut would crater the stock. Regulatory scrutiny of private credit opacity is an emerging risk.",
	"cagrModel": {
		"epsGrowth": "23%",
		"basis": "FRE per share",
		"ttmEPS": 5.94,
		"dividendYield": "4%",
		"scenarios": {
			"bear": "1%",
			"base": "17%",
			"bull": "52%"
		},
		"epsGrowthSource": "auto"
	},
	"currentPrice": "$128.50",
	"marketCap": "$42.4B USD",
	"valuation": {
		"trailingPE": 21.6,
		"forwardPE": 17.6,
		"evEbitda": 34.4,
		"evFcf": 27,
		"pegRatio": 1.05
	},
	"metrics": {
		"roe": "14.2%",
		"fcfMargin": "~30%",
		"fcfYield": "~4%",
		"netDebtEbitda": "9.2x",
		"ruleOf40": "58%",
		"beta": "1.52",
		"revenueGrowth": "28.3%",
		"roic": "3.0%",
		"interestCoverage": "1.8x"
	},
	"consensus": {
		"yahoo": "$145.35"
	},
	"targetPrice": "$145.35",
	"expectedCAGR": "1% - 52%",
	"screener": {
		"engine": "fFREG",
		"score": 0.94,
		"signal": "WAIT",
		"note": "Borderline valuation (Score 0.94 vs 0.8 limit)",
		"inputs": {
			"growth": 23,
			"multipleType": "P/FRE",
			"multiple": 21.6,
			"cvStock": 0.053,
			"riskMultiplier": 1
		},
		"realityChecks": {
			"stabilization": {
				"pass": true,
				"price": 128.5,
				"price6mAgo": 159.51,
				"price1mAgo": 119,
				"low3m": 95.8,
				"return6m": -19.4,
				"return1m": 8,
				"near3mLow": false
			},
			"revisions": {
				"pass": true,
				"up30d": 5,
				"down30d": 7
			},
			"earningsSurprise": {
				"surprise": -6.6,
				"quarter": "2026-03"
			}
		},
		"secondaryEngine": "fPERG",
		"secondaryScore": 0.77
	},
	"lastUpdated": "2026-06-01T00:56:28.580Z",
	"expectedVolatility": "~41%",
	"sharpeRatio": 0.54,
	"qcs": {
		"earningsScore": -4.22,
		"flowScore": 5,
		"revisionsScore": -0.83,
		"totalScore": -0.05,
		"raw": {
			"avgSurprisePct": -5.59,
			"netInsiderShares": 674637,
			"instFlowTrend": "positive",
			"upRevisions": 4,
			"downRevisions": 6,
			"totalAnalysts": 12
		}
	},
	"description": "Ares Management Corporation operates as an alternative asset manager.",
	"analystTargets": {
		"low": 125,
		"mean": 145.35,
		"high": 190
	},
	"analystConsensus": {
		"ticker": "ARES",
		"strongBuy": 5,
		"moderateBuy": 8,
		"hold": 8,
		"moderateSell": 2,
		"strongSell": 1
	},
	"consensusRating": "Moderate Buy",
	"forwardEstimates": {
		"2026": {
			"high": 6.07,
			"low": 5.75557,
			"average": 5.94071
		},
		"2027": {
			"high": 8.37,
			"low": 6.81449,
			"average": 7.32039
		}
	},
	"confidence": "cut"
}
