{
	"ticker": "EQT.ST",
	"name": "EQT AB",
	"group": "Financials & Alt Assets",
	"marketCap": "353.7B SEK",
	"sharpeRatio": 0.65,
	"expectedCAGR": "8% - 45%",
	"expectedVolatility": "~34%",
	"valuation": {
		"trailingPE": 241.4,
		"forwardPE": 20.7,
		"pegRatio": 0.84,
		"evEbitda": null,
		"priceToFRE": "~21.0x",
		"evFcf": 289.3
	},
	"metrics": {
		"fcfMargin": "~46%",
		"fcfYield": "~0%",
		"roic": "0.1%",
		"roe": "9.3%",
		"netDebtEbitda": "Net cash",
		"ruleOf40": "42%",
		"realizedExitsLTM": "€19B",
		"aumGrowth": "~12% YoY",
		"beta": "1.41",
		"revenueGrowth": "-4.3%",
		"interestCoverage": "9.7x"
	},
	"targetPrice": "381 SEK",
	"bullCase": "Europe's premier private equity firm. Strong fundraising momentum and a strategic push into Asia and retail wealth management channels provide a long, diversified runway for fee-related earnings growth.",
	"bearCase": "The European macro stagnation noted across the portfolio is toxic for private equity. If the European IPO and M&A exit windows freeze due to flat industrial output, EQT's carried interest will collapse, trapping capital.",
	"currentPrice": "302 SEK",
	"consensus": {
		"tipranks": "403 SEK",
		"yahoo": "381 SEK"
	},
	"cagrModel": {
		"ttmEPS": 13,
		"epsGrowth": "20%",
		"dividendYield": "2%",
		"scenarios": {
			"bear": "8%",
			"base": "28%",
			"bull": "45%"
		},
		"basis": "Fee-related earnings per share basis; exit PE reflects normalized FRE multiple rather than GAAP carried-interest swings"
	},
	"lastUpdated": "2026-04-30T00:44:36.073Z",
	"screener": {
		"engine": "fFREG",
		"score": 1.05,
		"signal": "REJECTED",
		"note": "Consensus actively collapsing (analyst lag)",
		"inputs": {
			"growth": 20,
			"multipleType": "P/FRE",
			"multiple": 21,
			"cvStock": 0.051,
			"riskMultiplier": 1
		},
		"realityChecks": {
			"stabilization": {
				"pass": true,
				"price": 302.2,
				"price6mAgo": 327.5,
				"price1mAgo": 283.6,
				"low3m": 262.1,
				"return6m": -7.7,
				"return1m": 6.6,
				"near3mLow": false
			},
			"revisions": {
				"pass": false,
				"up30d": 2,
				"down30d": 5
			}
		},
		"secondaryEngine": "fPERG",
		"secondaryScore": 1.03
	},
	"qcs": {
		"earningsScore": 0,
		"flowScore": 0,
		"revisionsScore": -3.5,
		"totalScore": -3.5,
		"raw": {
			"avgSurprisePct": 0,
			"netInsiderShares": 0,
			"instFlowTrend": "neutral",
			"upRevisions": 0,
			"downRevisions": 7,
			"totalAnalysts": 10
		}
	},
	"description": "EQT AB (publ) is a global private equity & venture capital firm specializing in private capital and real asset segments.",
	"analystTargets": {
		"low": 320.48,
		"mean": 380.92,
		"high": 431.77
	},
	"analystConsensus": {
		"ticker": "EQT.ST",
		"strongBuy": 0,
		"moderateBuy": 0,
		"hold": 0,
		"moderateSell": 0,
		"strongSell": 0
	},
	"consensusRating": "Unknown",
	"forwardEstimates": {
		"2026": {
			"high": 1.74981,
			"low": 0.97219,
			"average": 1.25193
		},
		"2027": {
			"high": 1.97985,
			"low": 1.61738,
			"average": 1.78007
		}
	},
	"confidence": "cut"
}
