{
	"ticker": "KKR",
	"name": "KKR & Co.",
	"group": "Financials & Alt Assets",
	"confidence": "low",
	"confidenceReason": "FRE margin ~69% on $638B AUM with permanent capital vehicle flywheel. Market misunderstands recurring permanent capital vehicle revenues.",
	"marketCap": "$82.0B USD",
	"sharpeRatio": 1.35,
	"expectedCAGR": "21% - 112%",
	"expectedVolatility": "~46%",
	"valuation": {
		"trailingPE": 13.8,
		"forwardPE": 11.3,
		"pegRatio": null,
		"evEbitda": null
	},
	"metrics": {
		"fcfMargin": null,
		"fcfYield": null,
		"roic": "0.5%",
		"roe": "8.6%",
		"netDebtEbitda": "N/M (consolidated)",
		"ruleOf40": "104%",
		"bessemerRuleOfX": "158%",
		"beta": "2.01",
		"revenueGrowth": "76.3%"
	},
	"targetPrice": "$135.77",
	"bullCase": "KKR earned $4.70 ANI/share in 2024 (+38% YoY) and is guiding to >$7 ANI/share by 2026. At $91, the stock trades at 19x trailing ANI — a steep discount to peers at 25–30x given the growth rate. AUM at $638B (+15% YoY) with $19B in embedded unrealised gains and a 69% FRE margin. The market is pricing this as a cyclical bank, not a permanent-capital compounding machine.",
	"bearCase": "Stock is down ~34% over the past 12 months. Performance fees are lumpy and exit markets can freeze for multiple years. The 3.7x net debt ratio amplifies interest rate sensitivity. If market volatility kills deal flow, carry distributions collapse and the premium multiple evaporates quickly.",
	"currentPrice": "$88.50",
	"consensus": {
		"tipranks": "$149",
		"yahoo": "$135.77",
		"stockanalysis": "$149"
	},
	"cagrModel": {
		"ttmEPS": 4.7,
		"epsGrowth": "20%",
		"dividendYield": "1%",
		"scenarios": {
			"bear": "21%",
			"base": "54%",
			"bull": "112%"
		},
		"basis": "ANI (Adjusted Net Income) per share; ANI P/E basis"
	},
	"lastUpdated": "2026-03-28T23:02:54.552Z",
	"screener": {
		"engine": "fANIG",
		"score": 0.94,
		"signal": "REJECTED",
		"inputs": {
			"growth": 20,
			"multipleType": "P/ANI",
			"multiple": 18.8,
			"cvStock": 0.048,
			"riskMultiplier": 1
		},
		"note": "Consensus actively collapsing (analyst lag)",
		"realityChecks": {
			"stabilization": {
				"pass": true,
				"price": 88.5,
				"price6mAgo": 134.48,
				"price1mAgo": 90.61,
				"low3m": 82.67,
				"return6m": -34.2,
				"return1m": -2.3,
				"near3mLow": false
			},
			"revisions": {
				"pass": false,
				"up30d": 0,
				"down30d": 6
			},
			"earningsSurprise": {
				"surprise": -1.6,
				"quarter": "2025-12"
			}
		},
		"secondaryEngine": "fPERG",
		"secondaryScore": 0.57
	},
	"qcs": {
		"earningsScore": 2.56,
		"flowScore": 2.5,
		"revisionsScore": -1.58,
		"totalScore": 3.48,
		"raw": {
			"avgSurprisePct": 3.08,
			"netInsiderShares": 0,
			"instFlowTrend": "positive",
			"upRevisions": 0,
			"downRevisions": 6,
			"totalAnalysts": 19
		}
	},
	"description": "KKR & Co. Inc.",
	"analystTargets": {
		"low": 106,
		"mean": 135.77,
		"high": 187
	},
	"analystConsensus": {
		"ticker": "KKR",
		"strongBuy": 5,
		"moderateBuy": 4,
		"hold": 4,
		"moderateSell": 2,
		"strongSell": 1
	},
	"consensusRating": "Moderate Buy",
	"targetPriceAlternative": "$149.01"
}
