{
	"ticker": "KNSL",
	"name": "Kinsale Capital",
	"group": "Insurance Compounders",
	"cyclical": true,
	"confidence": "high",
	"confidenceReason": "E&S insurer using proprietary tech to dominate niche. EPS compounds at 20–30% a year.",
	"bullCase": "Kinsale dominates E&S insurance through technology-driven underwriting that prices and binds risks faster than incumbents. ROE of 29% and combined ratio consistently below 85% give it a structural cost advantage. In a hard market, Kinsale's premium growth accelerates above 20%.",
	"bearCase": "A shift to a soft insurance market — driven by new capital entering E&S or a benign catastrophe cycle — compresses premiums and margins. At 16x forward PE, any slowdown below 15% EPS growth re-rates the stock. Competitors are investing heavily in E&S technology.",
	"cagrModel": {
		"epsGrowth": "20%",
		"basis": "Non-GAAP EPS",
		"ttmEPS": 21.65,
		"dividendYield": "0%",
		"scenarios": {
			"bear": "-5%",
			"base": "24%",
			"bull": "38%"
		}
	},
	"currentPrice": "$327.22",
	"marketCap": "$7.6B USD",
	"valuation": {
		"trailingPE": 15.1,
		"forwardPE": 14.7,
		"evEbitda": 11.7,
		"evFcf": 7.9
	},
	"metrics": {
		"roe": "29.3%",
		"fcfMargin": "~51%",
		"fcfYield": "~13%",
		"netDebtEbitda": "0.1x",
		"ruleOf40": "69%"
	},
	"consensus": {
		"yahoo": "$407.33"
	},
	"targetPrice": "$407.33",
	"expectedCAGR": "-5% - 38%",
	"screener": {
		"engine": "fPERG",
		"score": 0.74,
		"signal": "REJECTED",
		"inputs": {
			"growth": 20,
			"multipleType": "Forward P/E",
			"multiple": 14.7,
			"cvStock": 0.047,
			"riskMultiplier": 1
		},
		"note": "Consensus actively collapsing (analyst lag) (CYCLICAL EPS)",
		"realityChecks": {
			"stabilization": {
				"pass": false,
				"price": 327.22,
				"price6mAgo": 419.33,
				"price1mAgo": 382.46,
				"low3m": 321.97,
				"return6m": -22,
				"return1m": -14.4,
				"near3mLow": true
			},
			"revisions": {
				"pass": false,
				"up30d": 0,
				"down30d": 7
			},
			"earningsSurprise": {
				"surprise": 9.5,
				"quarter": "2025-12"
			}
		}
	},
	"lastUpdated": "2026-03-26T00:02:51.738Z",
	"expectedVolatility": "~38%",
	"sharpeRatio": 0.32,
	"qcs": {
		"earningsScore": 5,
		"flowScore": 5,
		"revisionsScore": -1.67,
		"totalScore": 8.33,
		"raw": {
			"avgSurprisePct": 9.8,
			"netInsiderShares": 23374,
			"instFlowTrend": "positive",
			"upRevisions": 3,
			"downRevisions": 7,
			"totalAnalysts": 12
		}
	},
	"description": "Kinsale Capital Group, Inc. engages in the provision of property and casualty insurance products in the United States.",
	"analystTargets": {
		"low": 312,
		"mean": 407.33,
		"high": 450
	}
}
