{
	"ticker": "MCK",
	"name": "McKesson",
	"group": "Healthcare Monopolies",
	"confidence": "medium",
	"confidenceReason": "Consolidated oligopoly drug distributor. Massive share repurchases lead to consistent 12–15% EPS growth floors.",
	"bullCase": "McKesson is a pharmaceutical distribution monopoly (with Cencora and Cardinal Health) distributing over 30% of US drug supply. The business is structurally non-disruptable — drug distribution requires regulatory compliance, cold chain, and scale economics that no new entrant can replicate. Systematic share buybacks (8%+ annual float reduction) drive 15%+ EPS growth on 5-7% revenue growth.",
	"bearCase": "Drug distribution is a razor-thin margin business — McKesson earns <1% net margin on $300B+ of drug revenue. Any repricing of generic drug contracts, specialty drug exclusivity losses, or government reimbursement rate cuts flows directly through to EPS. PBM consolidation increases buyer bargaining power against distributors.",
	"cagrModel": {
		"epsGrowth": "15%",
		"basis": "Non-GAAP EPS",
		"ttmEPS": 34.66,
		"dividendYield": "0%",
		"scenarios": {
			"bear": "-3%",
			"base": "13%",
			"bull": "25%"
		}
	},
	"currentPrice": "$884.28",
	"marketCap": "$109.1B USD",
	"valuation": {
		"trailingPE": 25.5,
		"forwardPE": 20,
		"evEbitda": 19.4,
		"evFcf": 12.6
	},
	"metrics": {
		"fcfMargin": "~2%",
		"fcfYield": "~8%",
		"netDebtEbitda": "1.0x",
		"ruleOf40": "14%",
		"beta": "0.42",
		"revenueGrowth": "11.4%",
		"roic": "9.1%",
		"interestCoverage": "12.3x"
	},
	"consensus": {
		"yahoo": "$997.67"
	},
	"targetPrice": "$997.67",
	"expectedCAGR": "-3% - 25%",
	"screener": {
		"engine": "fCFG",
		"score": 0.84,
		"signal": "REJECTED",
		"inputs": {
			"growth": 15,
			"multipleType": "EV/FCF",
			"multiple": 12.6,
			"cvStock": 0.01,
			"riskMultiplier": 1
		},
		"note": "REJECT: Stalled at WAIT with base CAGR 13% < 15%",
		"realityChecks": {
			"stabilization": {
				"pass": true,
				"price": 884.28,
				"price6mAgo": 741.29,
				"price1mAgo": 931.35,
				"low3m": 794.59,
				"return6m": 19.3,
				"return1m": -5.1,
				"near3mLow": false
			},
			"revisions": {
				"pass": true,
				"up30d": 2,
				"down30d": 0
			},
			"earningsSurprise": {
				"surprise": 0.7,
				"quarter": "2025-12"
			}
		},
		"secondaryEngine": "fPERG",
		"secondaryScore": 1.33
	},
	"lastUpdated": "2026-04-05T07:21:27.921Z",
	"expectedVolatility": "~28%",
	"sharpeRatio": 0.23,
	"qcs": {
		"earningsScore": 5,
		"flowScore": 0,
		"revisionsScore": 0.31,
		"totalScore": 5.31,
		"raw": {
			"avgSurprisePct": 3.5,
			"netInsiderShares": 756,
			"instFlowTrend": "negative",
			"upRevisions": 1,
			"downRevisions": 0,
			"totalAnalysts": 16
		}
	},
	"description": "McKesson Corporation provides healthcare services in the United States and internationally.",
	"analystTargets": {
		"low": 860,
		"mean": 997.67,
		"high": 1107
	},
	"analystConsensus": {
		"ticker": "MCK",
		"strongBuy": 5,
		"moderateBuy": 4,
		"hold": 4,
		"moderateSell": 2,
		"strongSell": 1
	},
	"consensusRating": "Moderate Buy",
	"targetPriceAlternative": "$960.93",
	"forwardEstimates": {
		"2026": {
			"high": 39.10129,
			"low": 38.94,
			"average": 39.02287
		},
		"2027": {
			"high": 44.78,
			"low": 43.07,
			"average": 44.23371
		}
	}
}
