{
	"ticker": "MELI",
	"name": "MercadoLibre",
	"group": "Emerging Markets",
	"confidence": "high",
	"confidenceReason": "LatAm e-commerce and fintech dominant platform, 24-39% EPS growth expected.",
	"marketCap": "$86.7B USD",
	"sharpeRatio": 0.03,
	"expectedCAGR": "-1% - 12%",
	"expectedVolatility": "~39%",
	"valuation": {
		"trailingPE": 43.4,
		"forwardPE": 22.1,
		"evEbitda": 22.3
	},
	"metrics": {
		"roe": "36.0%",
		"fcfMargin": "~-8%",
		"fcfYield": "~-3%",
		"netDebtEbitda": "1.3x",
		"ruleOf40": "36%"
	},
	"targetPrice": "$2658.92",
	"bullCase": "Dismantling LatAm legacy banking/retail structures with massive customer acquisition and elite capital efficiency. High ROE and rapid EPS growth.",
	"bearCase": "Highly correlated to local central bank rates and currency devaluation in emerging markets.",
	"currentPrice": "$1709.61",
	"cagrModel": {
		"scenarios": {
			"bear": "-1%",
			"base": "6%",
			"bull": "12%"
		},
		"ttmEPS": 39.38,
		"horizon": 5,
		"epsGrowth": "25%",
		"dividendYield": "0%",
		"exitPE": {
			"bear": 25,
			"base": 35,
			"bull": 45
		},
		"basis": "High-growth e-commerce/fintech normalized PE"
	},
	"lastUpdated": "2026-03-16T14:23:14.011Z",
	"consensus": {
		"yahoo": "$2658.92"
	},
	"screener": {
		"engine": "fPERG",
		"score": 0.91,
		"signal": "FAIL",
		"inputs": {
			"growth": 25,
			"multipleType": "Forward P/E",
			"multiple": 22.1,
			"cvStock": 0.123,
			"riskMultiplier": 1.026
		},
		"note": "Cheap (0.91) but base CAGR 6% misses the 14% hurdle"
	}
}
