{
	"ticker": "NVDA",
	"name": "NVIDIA",
	"group": "AI & Semiconductors",
	"cyclical": true,
	"confidence": "high",
	"confidenceReason": "Massive discount to peers (36x vs 80.7x avg). CAGR 22-28%. Vera Rubin platform implies $40B upside to consensus. Deeply entrenched value-compounder.",
	"marketCap": "$4384.6B USD",
	"sharpeRatio": 0.98,
	"expectedCAGR": "-22% - 111%",
	"expectedVolatility": "~41%",
	"valuation": {
		"trailingPE": 36.7,
		"forwardPE": 16.2,
		"pegRatio": 1.6,
		"evEbitda": 32.5
	},
	"metrics": {
		"fcfMargin": "~27%",
		"fcfYield": "~1%",
		"roic": null,
		"roe": "101.5%",
		"netDebtEbitda": "Net cash",
		"ruleOf40": "100%"
	},
	"targetPrice": "$268.43",
	"bullCase": "NVIDIA is generating the highest quality earnings in semiconductor history but trades at a massive discount to peers (36x vs 80.7x). The upcoming Vera Rubin platform (H2 2026) promises a 5x inference improvement, implying a $40B upside to consensus. It is now a deeply entrenched value-compounder.",
	"bearCase": "The trailing PEG ratio has expanded to 1.6x, indicating hyper-growth percentage gains are mathematically exhausting. If hyperscaler CapEx draws down, the cyclical shock will be violent.",
	"currentPrice": "$180.40",
	"consensus": {
		"tipranks": "$272",
		"yahoo": "$268.43",
		"stockanalysis": "$263"
	},
	"cagrModel": {
		"ttmEPS": 4.91,
		"epsGrowth": "29%",
		"dividendYield": "0%",
		"scenarios": {
			"bear": "-22%",
			"base": "49%",
			"bull": "111%"
		},
		"basis": "Reflects near-term EPS acceleration while normalizing longer-term terminal valuation."
	},
	"lastUpdated": "2026-03-19T13:06:41.976Z",
	"screener": {
		"engine": "fPERG",
		"score": 0.57,
		"signal": "PASS",
		"inputs": {
			"growth": 29,
			"multipleType": "Forward P/E",
			"multiple": 16.2,
			"cvStock": 0.128,
			"riskMultiplier": 1.029
		},
		"realityChecks": {
			"stabilization": {
				"pass": true,
				"price": 180.4,
				"price6mAgo": 176.67,
				"price1mAgo": 187.9,
				"low3m": 170.31,
				"return6m": 2.1,
				"return1m": -4,
				"near3mLow": false
			},
			"revisions": {
				"pass": true,
				"up30d": 26,
				"down30d": 5
			},
			"earningsSurprise": {
				"surprise": 5.3,
				"quarter": "2026-01"
			}
		},
		"note": "(CYCLICAL EPS)"
	},
	"intrinsicValue": {
		"dcf": 234.57,
		"date": "2026-03-19",
		"discount": 30
	},
	"qcs": {
		"earningsScore": 1.63,
		"flowScore": -5,
		"revisionsScore": 3.09,
		"totalScore": -0.28,
		"raw": {
			"avgSurprisePct": 5.22,
			"netInsiderShares": -2498471,
			"instFlowTrend": "negative",
			"upRevisions": 36,
			"downRevisions": 7,
			"totalAnalysts": 47
		}
	},
	"description": "NVIDIA Corporation operates as a data center scale AI infrastructure company.",
	"analystTargets": {
		"low": 140,
		"mean": 268.43,
		"high": 380
	}
}
