{
	"ticker": "PDD",
	"name": "PDD Holdings",
	"group": "Emerging Markets",
	"confidence": "low",
	"confidenceReason": "Incredible growth and cash flow, but severe geopolitical and regulatory risks.",
	"targetPrice": "$142.60",
	"bullCase": "PDD Holdings runs the most efficient e-commerce operation in China (50%+ EBIT margin) while Temu is executing aggressive global expansion. If Temu captures 5% of global cross-border e-commerce, incremental revenue could be $40-60B by 2030. The trailing P/E of 9x prices in a permanent growth halt that fundamentals don't support.",
	"bearCase": "Temu faces existential tariff risk: US de minimis exemption elimination and 145% tariffs make the sub-$15 product model unprofitable. Pinduoduo's domestic dominance may also erode as JD and Alibaba match its price-discovery algorithm.",
	"cagrModel": {
		"epsGrowth": "18%",
		"basis": "GAAP diluted EPS",
		"dividendYield": "0%",
		"ttmEPS": 9.71,
		"scenarios": {
			"bear": "10%",
			"base": "43%",
			"bull": "104%"
		}
	},
	"currentPrice": "$99.81",
	"marketCap": "$141.7B USD",
	"consensus": {
		"yahoo": "$142.60"
	},
	"expectedVolatility": "~36%",
	"screener": {
		"engine": "fEVG",
		"signal": "NO_DATA",
		"note": "Missing/negative EV/EBITDA"
	},
	"lastUpdated": "2026-03-28T23:03:03.953Z",
	"valuation": {
		"trailingPE": 10.3,
		"forwardPE": 7,
		"evEbitda": null,
		"evFcf": 1.7
	},
	"metrics": {
		"roe": "27.3%",
		"fcfMargin": "~19%",
		"fcfYield": "~59%",
		"netDebtEbitda": "Net cash",
		"ruleOf40": "31%",
		"beta": "0.05",
		"revenueGrowth": "12.0%",
		"interestCoverage": "322.3x"
	},
	"expectedCAGR": "10% - 104%",
	"sharpeRatio": 1.46,
	"qcs": {
		"earningsScore": 2.59,
		"flowScore": 2.5,
		"revisionsScore": -0.17,
		"totalScore": 4.92,
		"raw": {
			"avgSurprisePct": 5.17,
			"netInsiderShares": 0,
			"instFlowTrend": "positive",
			"upRevisions": 0,
			"downRevisions": 1,
			"totalAnalysts": 30
		}
	},
	"description": "PDD Holdings Inc., a multinational commerce group that owns and operates a portfolio of businesses.",
	"analystTargets": {
		"low": 109.71,
		"mean": 142.6,
		"high": 203.96
	},
	"analystConsensus": {
		"ticker": "PDD",
		"strongBuy": 10,
		"moderateBuy": 4,
		"hold": 10,
		"moderateSell": 2,
		"strongSell": 1
	},
	"targetPriceAlternative": "$140.57",
	"consensusRating": "Hold"
}
