{
	"ticker": "SE",
	"name": "Sea Limited",
	"group": "Emerging Markets",
	"targetPrice": "$137.64",
	"bullCase": "Sea Limited holds dominant positions across Southeast Asia in e-commerce (Shopee), digital financial services (SeaMoney), and gaming (Garena). SeaMoney's fintech penetration into underbanked EM populations mirrors the Nu Holdings playbook at scale. If Shopee achieves 15%+ EBIT margins at maturity — already visible in select markets — intrinsic value dramatically exceeds current pricing. The 22x exit P/E represents a modest premium for a dominant EM platform.",
	"bearCase": "Garena is structurally declining as Free Fire ages and new title launches repeatedly disappoint. TikTok Shop is aggressively competing with Shopee across SEA markets with superior content monetization. SeaMoney faces rising NPL risk in EM credit. The -54% 6-month return reflects genuine fundamental deterioration, not pure macro.",
	"cagrModel": {
		"epsGrowth": "22%",
		"basis": "GAAP diluted EPS",
		"dividendYield": "0%",
		"ttmEPS": 2.52,
		"scenarios": {
			"bear": "9%",
			"base": "65%",
			"bull": "134%"
		}
	},
	"currentPrice": "$83.21",
	"marketCap": "$51.0B USD",
	"consensus": {
		"yahoo": "$137.64"
	},
	"expectedVolatility": "~49%",
	"screener": {
		"engine": "fPERG",
		"score": 0.76,
		"signal": "PASS",
		"inputs": {
			"growth": 22,
			"multipleType": "Forward P/E",
			"multiple": 16.6,
			"cvStock": 0.122,
			"riskMultiplier": 1.007
		},
		"realityChecks": {
			"stabilization": {
				"pass": true,
				"price": 83.21,
				"price6mAgo": 155.93,
				"price1mAgo": 78.31,
				"low3m": 77.05,
				"return6m": -46.6,
				"return1m": 6.3,
				"near3mLow": false
			},
			"revisions": {
				"pass": true,
				"up30d": 1,
				"down30d": 1
			},
			"earningsSurprise": {
				"surprise": -5.5,
				"quarter": "2025-12"
			}
		}
	},
	"lastUpdated": "2026-04-30T00:44:46.600Z",
	"valuation": {
		"trailingPE": 33,
		"forwardPE": 16.6,
		"evEbitda": 18.6,
		"evFcf": 85.9,
		"pegRatio": 0.6
	},
	"metrics": {
		"roe": "15.3%",
		"fcfMargin": "~2%",
		"fcfYield": "~1%",
		"netDebtEbitda": "Net cash",
		"ruleOf40": "41%",
		"beta": "1.7",
		"revenueGrowth": "38.4%",
		"roic": "11.5%",
		"interestCoverage": "12.7x"
	},
	"expectedCAGR": "9% - 134%",
	"sharpeRatio": 1.37,
	"qcs": {
		"earningsScore": -3.13,
		"flowScore": 2.5,
		"revisionsScore": -1,
		"totalScore": -1.63,
		"raw": {
			"avgSurprisePct": -9.55,
			"netInsiderShares": -1568990,
			"instFlowTrend": "positive",
			"upRevisions": 0,
			"downRevisions": 2,
			"totalAnalysts": 10
		}
	},
	"description": "Sea Limited, through its subsidiaries, operates as a technology company in Southeast Asia, Latin America, the rest of Asia, and internationally.",
	"analystTargets": {
		"low": 91,
		"mean": 137.64,
		"high": 195
	},
	"analystConsensus": {
		"ticker": "SE",
		"strongBuy": 5,
		"moderateBuy": 4,
		"hold": 3,
		"moderateSell": 2,
		"strongSell": 2
	},
	"consensusRating": "Moderate Buy",
	"targetPriceAlternative": "$166.83",
	"forwardEstimates": {
		"2026": {
			"high": 4.97661,
			"low": 3.06,
			"average": 3.82308
		},
		"2027": {
			"high": 6.42241,
			"low": 3.98,
			"average": 5.0059
		}
	},
	"confidence": "cut"
}
