{
	"ticker": "TW",
	"name": "Tradeweb",
	"group": "Data & Software Monopolies",
	"cyclical": true,
	"confidence": "high",
	"confidenceReason": "Electronic bond trading matching traditional voice-brokers. Asset-light, massive operating leverage.",
	"bullCase": "Tradeweb is systematically replacing voice-brokered bond trading with electronic protocols, growing market share in US Treasuries, IG credit, and rates derivatives. Commission-per-ticket is rising as automation reduces headcount costs for clients. At 30%+ revenue CAGR, it is taking share from both MKTX and legacy dealers simultaneously.",
	"bearCase": "At 28x forward PE, TW is priced for continued share gains in fixed income e-trading. If bond market volumes collapse (credit freeze, rate stability), revenue growth stalls. MKTX is fighting back in US credit and dealer internalization poses a long-term structural risk.",
	"cagrModel": {
		"epsGrowth": "15%",
		"basis": "Non-GAAP EPS",
		"ttmEPS": 3.67,
		"dividendYield": "0%",
		"scenarios": {
			"bear": "-7%",
			"base": "10%",
			"bull": "69%"
		}
	},
	"currentPrice": "$119.95",
	"marketCap": "$26.2B USD",
	"valuation": {
		"trailingPE": 32.7,
		"forwardPE": 26.7
	},
	"metrics": {
		"roe": "13.6%"
	},
	"consensus": {
		"yahoo": "$132.31"
	},
	"targetPrice": "$132.31",
	"expectedCAGR": "-7% - 69%",
	"screener": {
		"engine": "fPERG",
		"score": 1.74,
		"signal": "FAIL",
		"inputs": {
			"growth": 15,
			"multipleType": "Forward P/E",
			"multiple": 26.7,
			"cvStock": 0.045,
			"riskMultiplier": 0.979
		},
		"realityChecks": {
			"stabilization": {
				"pass": true,
				"price": 119.95,
				"price6mAgo": 110.98,
				"price1mAgo": 121.96,
				"low3m": 97.06,
				"return6m": 8.1,
				"return1m": -1.6,
				"near3mLow": false
			},
			"revisions": {
				"pass": true,
				"up30d": 2,
				"down30d": 1
			},
			"earningsSurprise": {
				"surprise": 3,
				"quarter": "2025-12"
			}
		},
		"note": "(CYCLICAL EPS)"
	},
	"lastUpdated": "2026-03-26T00:03:01.295Z",
	"expectedVolatility": "~30%",
	"sharpeRatio": 0.88,
	"qcs": {
		"earningsScore": 2.14,
		"flowScore": 5,
		"revisionsScore": 0.38,
		"totalScore": 7.52,
		"raw": {
			"avgSurprisePct": 2.41,
			"netInsiderShares": 342956,
			"instFlowTrend": "positive",
			"upRevisions": 2,
			"downRevisions": 1,
			"totalAnalysts": 13
		}
	},
	"description": "Tradeweb Markets Inc. builds and operates electronic marketplaces in the United States and internationally.",
	"analystTargets": {
		"low": 111,
		"mean": 132.31,
		"high": 203
	}
}
