{
	"ticker": "VRT",
	"name": "Vertiv Holdings",
	"group": "Industrial Monopolies",
	"cyclical": true,
	"confidence": "low",
	"confidenceReason": "AI data center power/cooling play. ROIC ~25%, revenue growing 27-29%, $15B backlog, orders up 252% YoY. But trading at ~72x trailing earnings means priced for perfection.",
	"marketCap": "$105.7B USD",
	"sharpeRatio": -0.3,
	"expectedCAGR": "-44% - 16%",
	"expectedVolatility": "~61%",
	"valuation": {
		"trailingPE": 81,
		"forwardPE": 34.5,
		"pegRatio": null,
		"evEbitda": 48.5,
		"evFcf": 74.9
	},
	"metrics": {
		"fcfMargin": "~14%",
		"fcfYield": "~1%",
		"roic": "~25%",
		"roe": "41.8%",
		"netDebtEbitda": "0.6x",
		"ruleOf40": "37%",
		"revenueGrowth": "22.7%",
		"backlog": "$15B",
		"orderGrowth": "252% YoY"
	},
	"targetPrice": "$267.83",
	"bullCase": "AI power/cooling infrastructure is essential and non-optional. 27-29% revenue growth with $15B backlog and orders up 252% YoY. ROIC of ~25% is solid for industrial. Market leader in mission-critical data center thermal management.",
	"bearCase": "Trading at ~72x trailing earnings means priced for perfection. Any miss in execution could cause violent multiple compression. Cyclical industrial stock dressed up as a growth story.",
	"currentPrice": "$276.16",
	"consensus": {
		"tipranks": "$280",
		"yahoo": "$267.83",
		"stockanalysis": "$217"
	},
	"cagrModel": {
		"ttmEPS": 6.01,
		"epsGrowth": "30%",
		"dividendYield": "0%",
		"scenarios": {
			"bear": "-44%",
			"base": "-3%",
			"bull": "16%"
		},
		"basis": "2026E adjusted EPS; AI infrastructure power and cooling multiple"
	},
	"lastUpdated": "2026-03-26T00:03:03.053Z",
	"screener": {
		"engine": "fPERG",
		"score": 1.18,
		"signal": "WAIT",
		"inputs": {
			"growth": 30,
			"multipleType": "Forward P/E",
			"multiple": 34.5,
			"cvStock": 0.125,
			"riskMultiplier": 1.027
		},
		"realityChecks": {
			"stabilization": {
				"pass": true,
				"price": 276.16,
				"price6mAgo": 138.62,
				"price1mAgo": 259.23,
				"low3m": 158.77,
				"return6m": 99.2,
				"return1m": 6.5,
				"near3mLow": false
			},
			"revisions": {
				"pass": true,
				"up30d": 16,
				"down30d": 0
			},
			"earningsSurprise": {
				"surprise": 4.9,
				"quarter": "2025-12"
			}
		},
		"note": "(CYCLICAL EPS)"
	},
	"qcs": {
		"earningsScore": 3.86,
		"flowScore": -5,
		"revisionsScore": 5,
		"totalScore": 3.86,
		"raw": {
			"avgSurprisePct": 12.05,
			"netInsiderShares": -158418,
			"instFlowTrend": "negative",
			"upRevisions": 22,
			"downRevisions": 0,
			"totalAnalysts": 22
		}
	},
	"description": "Vertiv Holdings Co designs, manufactures, and services critical digital infrastructure technologies and life cycle services for data centers, communication networks, and commercial and industrial e...",
	"analystTargets": {
		"low": 155,
		"mean": 267.83,
		"high": 320
	}
}
